Workbook

Sheet EXPOSURE
A1: BU | B1: Fund | C1: Company | D1: Market Value (USD) | E1: BICS CODE | F1: SECTOR CODE | G1: INDUSTRY GROUP CODE | H1: INDUSTRY CODE | I1: SUB INDUSTRY CODE | J1: SECTOR NAME | K1: INDUSTRY GROUP NAME | L1: INDUSTRY NAME | M1: SUB INDUSTRY NAME
A2: Credit | B2: ALTURAS II | C2: AEROMEXICO | D2: 18854900 | E2: 1711121010 | F2: 17 | G2: 1711 | H2: 171112 | I2: 17111210 | J2: =+IFERROR(VLOOKUP(F2,BD_GICS!A:B,2,0),"") -> Industrials | K2: =+IFERROR(VLOOKUP(G2,BD_GICS!C:D,2,0),"") -> Industrial Services | L2: =+IFERROR(VLOOKUP(H2,BD_GICS!E:F,2,0),"") -> Transportation & Logistics | M2: =+IFERROR(VLOOKUP(I2,BD_GICS!G:H,2,0),"") -> Airlines
A3: Credit | B3: ALTURAS II | C3: AEROPUERTO INTERNACIONAL DE QUITO | D3: 7912206.8 | E3: 3712 | F3: 37 | G3: 3712 | H3: 3712 | I3: 3712 | J3: =+IFERROR(VLOOKUP(F3,BD_GICS!A:B,2,0),"") -> Industrials | K3: =+IFERROR(VLOOKUP(G3,BD_GICS!C:D,2,0),"") -> Transportation & Logistics | L3: =+IFERROR(VLOOKUP(H3,BD_GICS!E:F,2,0),"") | M3: =+IFERROR(VLOOKUP(I3,BD_GICS!G:H,2,0),"")
A4: Credit | B4: ALTURAS II | C4: ALBANESI | D4: 8656216.5 | E4: 2010101110 | F4: 20 | G4: 2010 | H4: 201010 | I4: 20101011 | J4: =+IFERROR(VLOOKUP(F4,BD_GICS!A:B,2,0),"") -> Utilities | K4: =+IFERROR(VLOOKUP(G4,BD_GICS!C:D,2,0),"") -> Utilities | L4: =+IFERROR(VLOOKUP(H4,BD_GICS!E:F,2,0),"") -> Electric Utilities | M4: =+IFERROR(VLOOKUP(I4,BD_GICS!G:H,2,0),"") -> Power Generation
A5: Credit | B5: ALTURAS II | C5: ALTO MAIPO | D5: 8533429.7 | E5: 3411 | F5: 34 | G5: 3411 | H5: 3411 | I5: 3411 | J5: =+IFERROR(VLOOKUP(F5,BD_GICS!A:B,2,0),"") -> Energy | K5: =+IFERROR(VLOOKUP(G5,BD_GICS!C:D,2,0),"") -> Renewable Energy | L5: =+IFERROR(VLOOKUP(H5,BD_GICS!E:F,2,0),"") | M5: =+IFERROR(VLOOKUP(I5,BD_GICS!G:H,2,0),"")
A6: Credit | B6: ALTURAS II | C6: AUTOPISTAS DEL ATLANTICO | D6: 3516524.7 | E6: 1711131112 | F6: 17 | G6: 1711 | H6: 171113 | I6: 17111311 | J6: =+IFERROR(VLOOKUP(F6,BD_GICS!A:B,2,0),"") -> Industrials | K6: =+IFERROR(VLOOKUP(G6,BD_GICS!C:D,2,0),"") -> Industrial Services | L6: =+IFERROR(VLOOKUP(H6,BD_GICS!E:F,2,0),"") -> Engineering & Construction | M6: =+IFERROR(VLOOKUP(I6,BD_GICS!G:H,2,0),"") -> Infrastructure Construction
A7: Credit | B7: ALTURAS II | C7: CONSTELLATION | D7: 31583031 | E7: 3413 | F7: 34 | G7: 3413 | H7: 3413 | I7: 3413 | J7: =+IFERROR(VLOOKUP(F7,BD_GICS!A:B,2,0),"") -> Energy | K7: =+IFERROR(VLOOKUP(G7,BD_GICS!C:D,2,0),"") -> Oil & Gas Services & Equipment | L7: =+IFERROR(VLOOKUP(H7,BD_GICS!E:F,2,0),"") | M7: =+IFERROR(VLOOKUP(I7,BD_GICS!G:H,2,0),"")
A8: Credit | B8: ALTURAS II | C8: LATINA OFFSHORE | D8: 22708395 | E8: 13101110 | F8: 13 | G8: 1310 | H8: 131011 | I8: 13101110 | J8: =+IFERROR(VLOOKUP(F8,BD_GICS!A:B,2,0),"") -> Energy | K8: =+IFERROR(VLOOKUP(G8,BD_GICS!C:D,2,0),"") -> Oil & Gas | L8: =+IFERROR(VLOOKUP(H8,BD_GICS!E:F,2,0),"") -> Oil & Gas Services & Equip | M8: =+IFERROR(VLOOKUP(I8,BD_GICS!G:H,2,0),"") -> Drilling & Drilling Support
A9: Credit | B9: ALTURAS II | C9: MSU ENERGY | D9: 2810091.3 | E9: 3911 | F9: 39 | G9: 3911 | H9: 3911 | I9: 3911 | J9: =+IFERROR(VLOOKUP(F9,BD_GICS!A:B,2,0),"") -> Utilities | K9: =+IFERROR(VLOOKUP(G9,BD_GICS!C:D,2,0),"") -> Power Generation | L9: =+IFERROR(VLOOKUP(H9,BD_GICS!E:F,2,0),"") | M9: =+IFERROR(VLOOKUP(I9,BD_GICS!G:H,2,0),"")
A10: Equity | B10: GLORY | C10: 3R PETROLEUM OLEO E GAS | D10: 5941498.9 | E10: 1310101110 | F10: 13 | G10: 1310 | H10: 131010 | I10: 13101011 | J10: =+IFERROR(VLOOKUP(F10,BD_GICS!A:B,2,0),"") -> Energy | K10: =+IFERROR(VLOOKUP(G10,BD_GICS!C:D,2,0),"") -> Oil & Gas | L10: =+IFERROR(VLOOKUP(H10,BD_GICS!E:F,2,0),"") -> Oil & Gas Producers | M10: =+IFERROR(VLOOKUP(I10,BD_GICS!G:H,2,0),"") -> Exploration & Production
A11: Equity | B11: GLORY | C11: AGUAS ANDINAS | D11: 1004211.1 | E11: 2010 | F11: 20 | G11: 2010 | H11: 2010 | I11: 2010 | J11: =+IFERROR(VLOOKUP(F11,BD_GICS!A:B,2,0),"") -> Utilities | K11: =+IFERROR(VLOOKUP(G11,BD_GICS!C:D,2,0),"") -> Utilities | L11: =+IFERROR(VLOOKUP(H11,BD_GICS!E:F,2,0),"") | M11: =+IFERROR(VLOOKUP(I11,BD_GICS!G:H,2,0),"")
A12: Equity | B12: GLORY | C12: AMBEV | D12: 3824532.9 | E12: 1210111010 | F12: 12 | G12: 1210 | H12: 121011 | I12: 12101110 | J12: =+IFERROR(VLOOKUP(F12,BD_GICS!A:B,2,0),"") -> Consumer Staples | K12: =+IFERROR(VLOOKUP(G12,BD_GICS!C:D,2,0),"") -> Consumer Staple Products | L12: =+IFERROR(VLOOKUP(H12,BD_GICS!E:F,2,0),"") -> Beverages | M12: =+IFERROR(VLOOKUP(I12,BD_GICS!G:H,2,0),"") -> Alcoholic Beverages
A13: Equity | B13: GLORY | C13: AMERICA MOVIL | D13: 3603756.9 | E13: 1011 | F13: 10 | G13: 1011 | H13: 1011 | I13: 1011 | J13: =+IFERROR(VLOOKUP(F13,BD_GICS!A:B,2,0),"") -> Communications | K13: =+IFERROR(VLOOKUP(G13,BD_GICS!C:D,2,0),"") -> Telecommunications | L13: =+IFERROR(VLOOKUP(H13,BD_GICS!E:F,2,0),"") | M13: =+IFERROR(VLOOKUP(I13,BD_GICS!G:H,2,0),"")
... A81: Equity | B81: GLORY | C81: WAL-MART MEXICO | D81: 4917073 | E81: 1211 | F81: 12 | G81: 1211 | H81: 1211 | I81: 1211 | J81: =+IFERROR(VLOOKUP(F81,BD_GICS!A:B,2,0),"") -> Consumer Staples | K81: =+IFERROR(VLOOKUP(G81,BD_GICS!C:D,2,0),"") -> Retail & Wholesale - Staples | L81: =+IFERROR(VLOOKUP(H81,BD_GICS!E:F,2,0),"") | M81: =+IFERROR(VLOOKUP(I81,BD_GICS!G:H,2,0),"")
A82: Credit | B82: MCCDF | C82: 522 FUNDING CLO | D82: 2476868 | E82: CLO | J82: =+IFERROR(VLOOKUP(F82,BD_GICS!A:B,2,0),"") | K82: =+IFERROR(VLOOKUP(G82,BD_GICS!C:D,2,0),"") | L82: =+IFERROR(VLOOKUP(H82,BD_GICS!E:F,2,0),"") | M82: =+IFERROR(VLOOKUP(I82,BD_GICS!G:H,2,0),"")
A83: Credit | B83: MCCDF | C83: ALLEGANY PARK CLO | D83: 1362329.4 | E83: CLO | J83: =+IFERROR(VLOOKUP(F83,BD_GICS!A:B,2,0),"") | K83: =+IFERROR(VLOOKUP(G83,BD_GICS!C:D,2,0),"") | L83: =+IFERROR(VLOOKUP(H83,BD_GICS!E:F,2,0),"") | M83: =+IFERROR(VLOOKUP(I83,BD_GICS!G:H,2,0),"")
A84: Credit | B84: MCCDF | C84: APIDOS CLO LTD | D84: 1053553.7 | E84: CLO | J84: =+IFERROR(VLOOKUP(F84,BD_GICS!A:B,2,0),"") | K84: =+IFERROR(VLOOKUP(G84,BD_GICS!C:D,2,0),"") | L84: =+IFERROR(VLOOKUP(H84,BD_GICS!E:F,2,0),"") | M84: =+IFERROR(VLOOKUP(I84,BD_GICS!G:H,2,0),"")
A85: Credit | B85: MCCDF | C85: ARBOUR CLO | D85: 2098636.2 | E85: CLO | J85: =+IFERROR(VLOOKUP(F85,BD_GICS!A:B,2,0),"") | K85: =+IFERROR(VLOOKUP(G85,BD_GICS!C:D,2,0),"") | L85: =+IFERROR(VLOOKUP(H85,BD_GICS!E:F,2,0),"") | M85: =+IFERROR(VLOOKUP(I85,BD_GICS!G:H,2,0),"")
A86: Credit | B86: MCCDF | C86: ARES CLO LTD | D86: 6109108.9 | E86: CLO | J86: =+IFERROR(VLOOKUP(F86,BD_GICS!A:B,2,0),"") | K86: =+IFERROR(VLOOKUP(G86,BD_GICS!C:D,2,0),"") | L86: =+IFERROR(VLOOKUP(H86,BD_GICS!E:F,2,0),"") | M86: =+IFERROR(VLOOKUP(I86,BD_GICS!G:H,2,0),"")
A87: Credit | B87: MCCDF | C87: BABSON CLO LTD | D87: 923139.63 | E87: CLO | J87: =+IFERROR(VLOOKUP(F87,BD_GICS!A:B,2,0),"") | K87: =+IFERROR(VLOOKUP(G87,BD_GICS!C:D,2,0),"") | L87: =+IFERROR(VLOOKUP(H87,BD_GICS!E:F,2,0),"") | M87: =+IFERROR(VLOOKUP(I87,BD_GICS!G:H,2,0),"")
A88: Credit | B88: MCCDF | C88: BAIN CAPITAL CREDIT CLO | D88: 1609238.2 | E88: CLO | J88: =+IFERROR(VLOOKUP(F88,BD_GICS!A:B,2,0),"") | K88: =+IFERROR(VLOOKUP(G88,BD_GICS!C:D,2,0),"") | L88: =+IFERROR(VLOOKUP(H88,BD_GICS!E:F,2,0),"") | M88: =+IFERROR(VLOOKUP(I88,BD_GICS!G:H,2,0),"")
A89: Credit | B89: MCCDF | C89: BEECHWOOD PARK CLO LTD | D89: 1879569.7 | E89: CLO | J89: =+IFERROR(VLOOKUP(F89,BD_GICS!A:B,2,0),"") | K89: =+IFERROR(VLOOKUP(G89,BD_GICS!C:D,2,0),"") | L89: =+IFERROR(VLOOKUP(H89,BD_GICS!E:F,2,0),"") | M89: =+IFERROR(VLOOKUP(I89,BD_GICS!G:H,2,0),"")
A90: Credit | B90: MCCDF | C90: CARLYLE GLOBAL MARKET | D90: 4009689.9 | E90: FUND | J90: =+IFERROR(VLOOKUP(F90,BD_GICS!A:B,2,0),"") | K90: =+IFERROR(VLOOKUP(G90,BD_GICS!C:D,2,0),"") | L90: =+IFERROR(VLOOKUP(H90,BD_GICS!E:F,2,0),"") | M90: =+IFERROR(VLOOKUP(I90,BD_GICS!G:H,2,0),"")
A91: Credit | B91: MCCDF | C91: CIFC EUROPEAN FUNDING CLO | D91: 2676416.9 | E91: CLO | J91: =+IFERROR(VLOOKUP(F91,BD_GICS!A:B,2,0),"") | K91: =+IFERROR(VLOOKUP(G91,BD_GICS!C:D,2,0),"") | L91: =+IFERROR(VLOOKUP(H91,BD_GICS!E:F,2,0),"") | M91: =+IFERROR(VLOOKUP(I91,BD_GICS!G:H,2,0),"")
A92: Credit | B92: MCCDF | C92: CORDATUS CLO PLC | D92: 6172086.4 | E92: CLO | J92: =+IFERROR(VLOOKUP(F92,BD_GICS!A:B,2,0),"") | K92: =+IFERROR(VLOOKUP(G92,BD_GICS!C:D,2,0),"") | L92: =+IFERROR(VLOOKUP(H92,BD_GICS!E:F,2,0),"") | M92: =+IFERROR(VLOOKUP(I92,BD_GICS!G:H,2,0),"")
A93: Credit | B93: MCCDF | C93: INVESCO CLO 2021-1 | D93: 2832682.2 | E93: CLO | J93: =+IFERROR(VLOOKUP(F93,BD_GICS!A:B,2,0),"") | K93: =+IFERROR(VLOOKUP(G93,BD_GICS!C:D,2,0),"") | L93: =+IFERROR(VLOOKUP(H93,BD_GICS!E:F,2,0),"") | M93: =+IFERROR(VLOOKUP(I93,BD_GICS!G:H,2,0),"")
... A100: Credit | B100: MCCDF | C100: PENTA CLO SA | D100: 4306143.7 | E100: CLO | J100: =+IFERROR(VLOOKUP(F100,BD_GICS!A:B,2,0),"") | K100: =+IFERROR(VLOOKUP(G100,BD_GICS!C:D,2,0),"") | L100: =+IFERROR(VLOOKUP(H100,BD_GICS!E:F,2,0),"") | M100: =+IFERROR(VLOOKUP(I100,BD_GICS!G:H,2,0),"")
A101: Credit | B101: MCCDF | C101: RISERVA | D101: 4321986.5 | E101: 1411 | F101: 14 | G101: 1411 | H101: 1411 | I101: 1411 | J101: =+IFERROR(VLOOKUP(F101,BD_GICS!A:B,2,0),"") -> Financials | K101: =+IFERROR(VLOOKUP(G101,BD_GICS!C:D,2,0),"") -> Financial Services | L101: =+IFERROR(VLOOKUP(H101,BD_GICS!E:F,2,0),"") | M101: =+IFERROR(VLOOKUP(I101,BD_GICS!G:H,2,0),"")
A102: Credit | B102: MCCDF | C102: ROCKFORD TOWER CLO 2022-1 | D102: 2712314.4 | E102: CLO | J102: =+IFERROR(VLOOKUP(F102,BD_GICS!A:B,2,0),"") | K102: =+IFERROR(VLOOKUP(G102,BD_GICS!C:D,2,0),"") | L102: =+IFERROR(VLOOKUP(H102,BD_GICS!E:F,2,0),"") | M102: =+IFERROR(VLOOKUP(I102,BD_GICS!G:H,2,0),"")
A103: Credit | B103: MCCDF | C103: VOYA EURO CLO | D103: 1326093.9 | E103: CLO | J103: =+IFERROR(VLOOKUP(F103,BD_GICS!A:B,2,0),"") | K103: =+IFERROR(VLOOKUP(G103,BD_GICS!C:D,2,0),"") | L103: =+IFERROR(VLOOKUP(H103,BD_GICS!E:F,2,0),"") | M103: =+IFERROR(VLOOKUP(I103,BD_GICS!G:H,2,0),"")
A104: Credit | B104: MCCDF | C104: WIND RIVER CLO | D104: 4328922.2 | E104: CLO | J104: =+IFERROR(VLOOKUP(F104,BD_GICS!A:B,2,0),"") | K104: =+IFERROR(VLOOKUP(G104,BD_GICS!C:D,2,0),"") | L104: =+IFERROR(VLOOKUP(H104,BD_GICS!E:F,2,0),"") | M104: =+IFERROR(VLOOKUP(I104,BD_GICS!G:H,2,0),"")
A105: Credit | B105: MCPPP | C105: ABASTIBLE | D105: 158396.36 | E105: 20101110 | F105: 20 | G105: 2010 | H105: 201011 | I105: 20101110 | J105: =+IFERROR(VLOOKUP(F105,BD_GICS!A:B,2,0),"") -> Utilities | K105: =+IFERROR(VLOOKUP(G105,BD_GICS!C:D,2,0),"") -> Utilities | L105: =+IFERROR(VLOOKUP(H105,BD_GICS!E:F,2,0),"") -> Gas & Water Utilities | M105: =+IFERROR(VLOOKUP(I105,BD_GICS!G:H,2,0),"") -> Gas Utilities
A106: Credit | B106: MCPPP | C106: AD RETAIL | D106: 642590.93 | E106: 3231 | F106: 32 | G106: 3231 | H106: 3231 | I106: 3231 | J106: =+IFERROR(VLOOKUP(F106,BD_GICS!A:B,2,0),"") -> Consumer Discretionary | K106: =+IFERROR(VLOOKUP(G106,BD_GICS!C:D,2,0),"") -> Department Stores | L106: =+IFERROR(VLOOKUP(H106,BD_GICS!E:F,2,0),"") | M106: =+IFERROR(VLOOKUP(I106,BD_GICS!G:H,2,0),"")
A107: Credit | B107: MCPPP | C107: AGROSUPER | D107: 3708.1738 | E107: 1211101116 | F107: 12 | G107: 1211 | H107: 121110 | I107: 12111011 | J107: =+IFERROR(VLOOKUP(F107,BD_GICS!A:B,2,0),"") -> Consumer Staples | K107: =+IFERROR(VLOOKUP(G107,BD_GICS!C:D,2,0),"") -> Retail & Wholesale - Staples | L107: =+IFERROR(VLOOKUP(H107,BD_GICS!E:F,2,0),"") -> Wholesale - Consumer Staples | M107: =+IFERROR(VLOOKUP(I107,BD_GICS!G:H,2,0),"") -> Food & Beverage Wholesalers
A108: Credit | B108: MCPPP | C108: AGUAS ANDINAS | D108: 10235.398 | E108: 2010 | F108: 20 | G108: 2010 | H108: 2010 | I108: 2010 | J108: =+IFERROR(VLOOKUP(F108,BD_GICS!A:B,2,0),"") -> Utilities | K108: =+IFERROR(VLOOKUP(G108,BD_GICS!C:D,2,0),"") -> Utilities | L108: =+IFERROR(VLOOKUP(H108,BD_GICS!E:F,2,0),"") | M108: =+IFERROR(VLOOKUP(I108,BD_GICS!G:H,2,0),"")
A109: Credit | B109: MCPPP | C109: AGUAS ARAUCANIA | D109: 112574.25 | E109: 20101111 | F109: 20 | G109: 2010 | H109: 201011 | I109: 20101111 | J109: =+IFERROR(VLOOKUP(F109,BD_GICS!A:B,2,0),"") -> Utilities | K109: =+IFERROR(VLOOKUP(G109,BD_GICS!C:D,2,0),"") -> Utilities | L109: =+IFERROR(VLOOKUP(H109,BD_GICS!E:F,2,0),"") -> Gas & Water Utilities | M109: =+IFERROR(VLOOKUP(I109,BD_GICS!G:H,2,0),"") -> Water Utilities
A110: Credit | B110: MCPPP | C110: ANGLO AMERICAN | D110: 101860.13 | E110: 1810151211 | F110: 18 | G110: 1810 | H110: 181015 | I110: 18101512 | J110: =+IFERROR(VLOOKUP(F110,BD_GICS!A:B,2,0),"") -> Materials | K110: =+IFERROR(VLOOKUP(G110,BD_GICS!C:D,2,0),"") -> Materials | L110: =+IFERROR(VLOOKUP(H110,BD_GICS!E:F,2,0),"") -> Metals & Mining | M110: =+IFERROR(VLOOKUP(I110,BD_GICS!G:H,2,0),"") -> Precious Metals
A111: Credit | B111: MCPPP | C111: ANTOFAGASTA MINERALS | D111: 587447.78 | E111: 3011 | F111: 30 | G111: 3011 | H111: 3011 | I111: 3011 | J111: =+IFERROR(VLOOKUP(F111,BD_GICS!A:B,2,0),"") -> Materials | K111: =+IFERROR(VLOOKUP(G111,BD_GICS!C:D,2,0),"") -> Metals & Mining | L111: =+IFERROR(VLOOKUP(H111,BD_GICS!E:F,2,0),"") | M111: =+IFERROR(VLOOKUP(I111,BD_GICS!G:H,2,0),"")
A112: Credit | B112: MCPPP | C112: AQUACHILE | D112: 2616.2805 | E112: 1210101115 | F112: 12 | G112: 1210 | H112: 121010 | I112: 12101011 | J112: =+IFERROR(VLOOKUP(F112,BD_GICS!A:B,2,0),"") -> Consumer Staples | K112: =+IFERROR(VLOOKUP(G112,BD_GICS!C:D,2,0),"") -> Consumer Staple Products | L112: =+IFERROR(VLOOKUP(H112,BD_GICS!E:F,2,0),"") -> Food | M112: =+IFERROR(VLOOKUP(I112,BD_GICS!G:H,2,0),"") -> Packaged Food
A113: Credit | B113: MCPPP | C113: BANCO CHILE | D113: 20325.861 | E113: 1410101111 | F113: 14 | G113: 1410 | H113: 141010 | I113: 14101011 | J113: =+IFERROR(VLOOKUP(F113,BD_GICS!A:B,2,0),"") -> Financials | K113: =+IFERROR(VLOOKUP(G113,BD_GICS!C:D,2,0),"") -> Banking | L113: =+IFERROR(VLOOKUP(H113,BD_GICS!E:F,2,0),"") -> Banking | M113: =+IFERROR(VLOOKUP(I113,BD_GICS!G:H,2,0),"") -> Banks
A114: Credit | B114: MCPPP | C114: BESALCO | D114: 736219.51 | E114: 17111312 | F114: 17 | G114: 1711 | H114: 171113 | I114: 17111312 | J114: =+IFERROR(VLOOKUP(F114,BD_GICS!A:B,2,0),"") -> Industrials | K114: =+IFERROR(VLOOKUP(G114,BD_GICS!C:D,2,0),"") -> Industrial Services | L114: =+IFERROR(VLOOKUP(H114,BD_GICS!E:F,2,0),"") -> Engineering & Construction | M114: =+IFERROR(VLOOKUP(I114,BD_GICS!G:H,2,0),"") -> Building Construction
A115: Credit | B115: MCPPP | C115: BLUE EXPRESS | D115: 800204.53 | E115: 17111215 | F115: 17 | G115: 1711 | H115: 171112 | I115: 17111215 | J115: =+IFERROR(VLOOKUP(F115,BD_GICS!A:B,2,0),"") -> Industrials | K115: =+IFERROR(VLOOKUP(G115,BD_GICS!C:D,2,0),"") -> Industrial Services | L115: =+IFERROR(VLOOKUP(H115,BD_GICS!E:F,2,0),"") -> Transportation & Logistics | M115: =+IFERROR(VLOOKUP(I115,BD_GICS!G:H,2,0),"") -> Trucking
A116: Credit | B116: MCPPP | C116: BLUMAR | D116: 322021.99 | E116: 1210101012 | F116: 12 | G116: 1210 | H116: 121010 | I116: 12101010 | J116: =+IFERROR(VLOOKUP(F116,BD_GICS!A:B,2,0),"") -> Consumer Staples | K116: =+IFERROR(VLOOKUP(G116,BD_GICS!C:D,2,0),"") -> Consumer Staple Products | L116: =+IFERROR(VLOOKUP(H116,BD_GICS!E:F,2,0),"") -> Food | M116: =+IFERROR(VLOOKUP(I116,BD_GICS!G:H,2,0),"") -> Agricultural Producers
... A236: Credit | B236: MDCH | C236: TRANSELEC | D236: 38275.21 | E236: 2010101210 | F236: 20 | G236: 2010 | H236: 201010 | I236: 20101012 | J236: =+IFERROR(VLOOKUP(F236,BD_GICS!A:B,2,0),"") -> Utilities | K236: =+IFERROR(VLOOKUP(G236,BD_GICS!C:D,2,0),"") -> Utilities | L236: =+IFERROR(VLOOKUP(H236,BD_GICS!E:F,2,0),"") -> Electric Utilities | M236: =+IFERROR(VLOOKUP(I236,BD_GICS!G:H,2,0),"") -> Electric Transmission & Dist
A237: Credit | B237: MDCH | C237: VOLCOM SECURITIZADORA | D237: 2269891.2 | E237: FUND | J237: =+IFERROR(VLOOKUP(F237,BD_GICS!A:B,2,0),"") | K237: =+IFERROR(VLOOKUP(G237,BD_GICS!C:D,2,0),"") | L237: =+IFERROR(VLOOKUP(H237,BD_GICS!E:F,2,0),"") | M237: =+IFERROR(VLOOKUP(I237,BD_GICS!G:H,2,0),"")
A238: Credit | B238: MDCH | C238: WATTS | D238: 821701.16 | E238: 12101011 | F238: 12 | G238: 1210 | H238: 121010 | I238: 12101011 | J238: =+IFERROR(VLOOKUP(F238,BD_GICS!A:B,2,0),"") -> Consumer Staples | K238: =+IFERROR(VLOOKUP(G238,BD_GICS!C:D,2,0),"") -> Consumer Staple Products | L238: =+IFERROR(VLOOKUP(H238,BD_GICS!E:F,2,0),"") -> Food | M238: =+IFERROR(VLOOKUP(I238,BD_GICS!G:H,2,0),"") -> Packaged Food
A239: Credit | B239: MDCH | C239: WENCO | D239: 659829.77 | E239: 3014 | F239: 30 | G239: 3014 | H239: 3014 | I239: 3014 | J239: =+IFERROR(VLOOKUP(F239,BD_GICS!A:B,2,0),"") -> Materials | K239: =+IFERROR(VLOOKUP(G239,BD_GICS!C:D,2,0),"") -> Containers & Packaging | L239: =+IFERROR(VLOOKUP(H239,BD_GICS!E:F,2,0),"") | M239: =+IFERROR(VLOOKUP(I239,BD_GICS!G:H,2,0),"")
A240: Equity | B240: MDELA | C240: 3R PETROLEUM OLEO E GAS | D240: 22212.04 | E240: 1310101110 | F240: 13 | G240: 1310 | H240: 131010 | I240: 13101011 | J240: =+IFERROR(VLOOKUP(F240,BD_GICS!A:B,2,0),"") -> Energy | K240: =+IFERROR(VLOOKUP(G240,BD_GICS!C:D,2,0),"") -> Oil & Gas | L240: =+IFERROR(VLOOKUP(H240,BD_GICS!E:F,2,0),"") -> Oil & Gas Producers | M240: =+IFERROR(VLOOKUP(I240,BD_GICS!G:H,2,0),"") -> Exploration & Production
A241: Equity | B241: MDELA | C241: AGUAS ANDINAS | D241: 240919.95 | E241: 2010 | F241: 20 | G241: 2010 | H241: 2010 | I241: 2010 | J241: =+IFERROR(VLOOKUP(F241,BD_GICS!A:B,2,0),"") -> Utilities | K241: =+IFERROR(VLOOKUP(G241,BD_GICS!C:D,2,0),"") -> Utilities | L241: =+IFERROR(VLOOKUP(H241,BD_GICS!E:F,2,0),"") | M241: =+IFERROR(VLOOKUP(I241,BD_GICS!G:H,2,0),"")
A242: Equity | B242: MDELA | C242: ALSEA | D242: 615640.02 | E242: 1111111310 | F242: 11 | G242: 1111 | H242: 111111 | I242: 11111113 | J242: =+IFERROR(VLOOKUP(F242,BD_GICS!A:B,2,0),"") -> Consumer Discretionary | K242: =+IFERROR(VLOOKUP(G242,BD_GICS!C:D,2,0),"") -> Consumer Discretionary Services | L242: =+IFERROR(VLOOKUP(H242,BD_GICS!E:F,2,0),"") -> Leisure Facilities & Services | M242: =+IFERROR(VLOOKUP(I242,BD_GICS!G:H,2,0),"") -> Restaurants
A243: Equity | B243: MDELA | C243: AMBEV | D243: 23641.69 | E243: 1210111010 | F243: 12 | G243: 1210 | H243: 121011 | I243: 12101110 | J243: =+IFERROR(VLOOKUP(F243,BD_GICS!A:B,2,0),"") -> Consumer Staples | K243: =+IFERROR(VLOOKUP(G243,BD_GICS!C:D,2,0),"") -> Consumer Staple Products | L243: =+IFERROR(VLOOKUP(H243,BD_GICS!E:F,2,0),"") -> Beverages | M243: =+IFERROR(VLOOKUP(I243,BD_GICS!G:H,2,0),"") -> Alcoholic Beverages
A244: Equity | B244: MDELA | C244: AMERICA MOVIL | D244: 2392958.2 | E244: 1011 | F244: 10 | G244: 1011 | H244: 1011 | I244: 1011 | J244: =+IFERROR(VLOOKUP(F244,BD_GICS!A:B,2,0),"") -> Communications | K244: =+IFERROR(VLOOKUP(G244,BD_GICS!C:D,2,0),"") -> Telecommunications | L244: =+IFERROR(VLOOKUP(H244,BD_GICS!E:F,2,0),"") | M244: =+IFERROR(VLOOKUP(I244,BD_GICS!G:H,2,0),"")
A245: Equity | B245: MDELA | C245: ARCA CONTINENTAL | D245: 1186218.8 | E245: 1210111113 | F245: 12 | G245: 1210 | H245: 121011 | I245: 12101111 | J245: =+IFERROR(VLOOKUP(F245,BD_GICS!A:B,2,0),"") -> Consumer Staples | K245: =+IFERROR(VLOOKUP(G245,BD_GICS!C:D,2,0),"") -> Consumer Staple Products | L245: =+IFERROR(VLOOKUP(H245,BD_GICS!E:F,2,0),"") -> Beverages | M245: =+IFERROR(VLOOKUP(I245,BD_GICS!G:H,2,0),"") -> Non-Alcoholic Beverages
A246: Equity | B246: MDELA | C246: ARCOS DORADOS | D246: 906140.18 | E246: 3215 | F246: 32 | G246: 3215 | H246: 3215 | I246: 3215 | J246: =+IFERROR(VLOOKUP(F246,BD_GICS!A:B,2,0),"") -> Consumer Discretionary | K246: =+IFERROR(VLOOKUP(G246,BD_GICS!C:D,2,0),"") -> Restaurants | L246: =+IFERROR(VLOOKUP(H246,BD_GICS!E:F,2,0),"") | M246: =+IFERROR(VLOOKUP(I246,BD_GICS!G:H,2,0),"")
A247: Equity | B247: MDELA | C247: B3 | D247: 42253.96 | E247: 1411 | F247: 14 | G247: 1411 | H247: 1411 | I247: 1411 | J247: =+IFERROR(VLOOKUP(F247,BD_GICS!A:B,2,0),"") -> Financials | K247: =+IFERROR(VLOOKUP(G247,BD_GICS!C:D,2,0),"") -> Financial Services | L247: =+IFERROR(VLOOKUP(H247,BD_GICS!E:F,2,0),"") | M247: =+IFERROR(VLOOKUP(I247,BD_GICS!G:H,2,0),"")
A248: Equity | B248: MDELA | C248: BANCO BRADESCO | D248: 55937.81 | E248: 1410 | F248: 14 | G248: 1410 | H248: 1410 | I248: 1410 | J248: =+IFERROR(VLOOKUP(F248,BD_GICS!A:B,2,0),"") -> Financials | K248: =+IFERROR(VLOOKUP(G248,BD_GICS!C:D,2,0),"") -> Banking | L248: =+IFERROR(VLOOKUP(H248,BD_GICS!E:F,2,0),"") | M248: =+IFERROR(VLOOKUP(I248,BD_GICS!G:H,2,0),"")
A249: Equity | B249: MDELA | C249: BANCO BTG PACTUAL | D249: 19627.68 | E249: 1411 | F249: 14 | G249: 1411 | H249: 1411 | I249: 1411 | J249: =+IFERROR(VLOOKUP(F249,BD_GICS!A:B,2,0),"") -> Financials | K249: =+IFERROR(VLOOKUP(G249,BD_GICS!C:D,2,0),"") -> Financial Services | L249: =+IFERROR(VLOOKUP(H249,BD_GICS!E:F,2,0),"") | M249: =+IFERROR(VLOOKUP(I249,BD_GICS!G:H,2,0),"")
... A381: Credit | B381: MDLAT | C381: GENERAL SHOPPING | D381: 18815873 | E381: 1510101610 | F381: 15 | G381: 1510 | H381: 151010 | I381: 15101016 | J381: =+IFERROR(VLOOKUP(F381,BD_GICS!A:B,2,0),"") -> Real Estate | K381: =+IFERROR(VLOOKUP(G381,BD_GICS!C:D,2,0),"") -> Real Estate | L381: =+IFERROR(VLOOKUP(H381,BD_GICS!E:F,2,0),"") -> Real Estate Owners & Developers | M381: =+IFERROR(VLOOKUP(I381,BD_GICS!G:H,2,0),"") -> Retail Owners & Developers
A382: Credit | B382: MDLAT | C382: GENERAL SHOPPING FONDO INMOBILIARIO | D382: 5566.91 | E382: FUND | J382: =+IFERROR(VLOOKUP(F382,BD_GICS!A:B,2,0),"") | K382: =+IFERROR(VLOOKUP(G382,BD_GICS!C:D,2,0),"") | L382: =+IFERROR(VLOOKUP(H382,BD_GICS!E:F,2,0),"") | M382: =+IFERROR(VLOOKUP(I382,BD_GICS!G:H,2,0),"")
A383: Credit | B383: MDLAT | C383: GEOPARK | D383: 1657019.8 | E383: 1310101110 | F383: 13 | G383: 1310 | H383: 131010 | I383: 13101011 | J383: =+IFERROR(VLOOKUP(F383,BD_GICS!A:B,2,0),"") -> Energy | K383: =+IFERROR(VLOOKUP(G383,BD_GICS!C:D,2,0),"") -> Oil & Gas | L383: =+IFERROR(VLOOKUP(H383,BD_GICS!E:F,2,0),"") -> Oil & Gas Producers | M383: =+IFERROR(VLOOKUP(I383,BD_GICS!G:H,2,0),"") -> Exploration & Production
A384: Credit | B384: MDLAT | C384: GLOBO | D384: 3593998.7 | E384: 3115 | F384: 31 | G384: 3115 | H384: 3115 | I384: 3115 | J384: =+IFERROR(VLOOKUP(F384,BD_GICS!A:B,2,0),"") -> Communications | K384: =+IFERROR(VLOOKUP(G384,BD_GICS!C:D,2,0),"") -> Publishing & Broadcasting | L384: =+IFERROR(VLOOKUP(H384,BD_GICS!E:F,2,0),"") | M384: =+IFERROR(VLOOKUP(I384,BD_GICS!G:H,2,0),"")
A385: Credit | B385: MDLAT | C385: GOL LINHAS AEREAS | D385: 33474383 | E385: 3213 | F385: 32 | G385: 3213 | H385: 3213 | I385: 3213 | J385: =+IFERROR(VLOOKUP(F385,BD_GICS!A:B,2,0),"") -> Consumer Discretionary | K385: =+IFERROR(VLOOKUP(G385,BD_GICS!C:D,2,0),"") -> Airlines | L385: =+IFERROR(VLOOKUP(H385,BD_GICS!E:F,2,0),"") | M385: =+IFERROR(VLOOKUP(I385,BD_GICS!G:H,2,0),"")
A386: Credit | B386: MDLAT | C386: GOLIATH | D386: 0 | E386: 3712 | F386: 37 | G386: 3712 | H386: 3712 | I386: 3712 | J386: =+IFERROR(VLOOKUP(F386,BD_GICS!A:B,2,0),"") -> Industrials | K386: =+IFERROR(VLOOKUP(G386,BD_GICS!C:D,2,0),"") -> Transportation & Logistics | L386: =+IFERROR(VLOOKUP(H386,BD_GICS!E:F,2,0),"") | M386: =+IFERROR(VLOOKUP(I386,BD_GICS!G:H,2,0),"")
A387: Credit | B387: MDLAT | C387: GP INVESTMENTS | D387: 2698580.2 | E387: 3516 | F387: 35 | G387: 3516 | H387: 3516 | I387: 3516 | J387: =+IFERROR(VLOOKUP(F387,BD_GICS!A:B,2,0),"") -> Financials | K387: =+IFERROR(VLOOKUP(G387,BD_GICS!C:D,2,0),"") -> Financial Services | L387: =+IFERROR(VLOOKUP(H387,BD_GICS!E:F,2,0),"") | M387: =+IFERROR(VLOOKUP(I387,BD_GICS!G:H,2,0),"")
A388: Credit | B388: MDLAT | C388: GRUPO AVAL | D388: 6829382.3 | E388: 3510 | F388: 35 | G388: 3510 | H388: 3510 | I388: 3510 | J388: =+IFERROR(VLOOKUP(F388,BD_GICS!A:B,2,0),"") -> Financials | K388: =+IFERROR(VLOOKUP(G388,BD_GICS!C:D,2,0),"") -> Banks | L388: =+IFERROR(VLOOKUP(H388,BD_GICS!E:F,2,0),"") | M388: =+IFERROR(VLOOKUP(I388,BD_GICS!G:H,2,0),"")
A389: Credit | B389: MDLAT | C389: GRUPO GICSA | D389: 11136913 | E389: 3515 | F389: 35 | G389: 3515 | H389: 3515 | I389: 3515 | J389: =+IFERROR(VLOOKUP(F389,BD_GICS!A:B,2,0),"") -> Financials | K389: =+IFERROR(VLOOKUP(G389,BD_GICS!C:D,2,0),"") -> Real Estate | L389: =+IFERROR(VLOOKUP(H389,BD_GICS!E:F,2,0),"") | M389: =+IFERROR(VLOOKUP(I389,BD_GICS!G:H,2,0),"")
A390: Credit | B390: MDLAT | C390: GRUPO IDESA | D390: 243735.8 | E390: 3013 | F390: 30 | G390: 3013 | H390: 3013 | I390: 3013 | J390: =+IFERROR(VLOOKUP(F390,BD_GICS!A:B,2,0),"") -> Materials | K390: =+IFERROR(VLOOKUP(G390,BD_GICS!C:D,2,0),"") -> Chemicals | L390: =+IFERROR(VLOOKUP(H390,BD_GICS!E:F,2,0),"") | M390: =+IFERROR(VLOOKUP(I390,BD_GICS!G:H,2,0),"")
A391: Credit | B391: MDLAT | C391: GRUPO POSADAS | D391: 23426107 | E391: 3216 | F391: 32 | G391: 3216 | H391: 3216 | I391: 3216 | J391: =+IFERROR(VLOOKUP(F391,BD_GICS!A:B,2,0),"") -> Consumer Discretionary | K391: =+IFERROR(VLOOKUP(G391,BD_GICS!C:D,2,0),"") -> Travel & Lodging | L391: =+IFERROR(VLOOKUP(H391,BD_GICS!E:F,2,0),"") | M391: =+IFERROR(VLOOKUP(I391,BD_GICS!G:H,2,0),"")
A392: Credit | B392: MDLAT | C392: GUACOLDA ENERGIA | D392: 38674100 | E392: 3910 | F392: 39 | G392: 3910 | H392: 3910 | I392: 3910 | J392: =+IFERROR(VLOOKUP(F392,BD_GICS!A:B,2,0),"") -> Utilities | K392: =+IFERROR(VLOOKUP(G392,BD_GICS!C:D,2,0),"") -> Utilities | L392: =+IFERROR(VLOOKUP(H392,BD_GICS!E:F,2,0),"") | M392: =+IFERROR(VLOOKUP(I392,BD_GICS!G:H,2,0),"")
A393: Credit | B393: MDLAT | C393: HIPOTECARIA SU CASITA | D393: 10138.8 | E393: 3512 | F393: 35 | G393: 3512 | H393: 3512 | I393: 3512 | J393: =+IFERROR(VLOOKUP(F393,BD_GICS!A:B,2,0),"") -> Financials | K393: =+IFERROR(VLOOKUP(G393,BD_GICS!C:D,2,0),"") -> Consumer Finance | L393: =+IFERROR(VLOOKUP(H393,BD_GICS!E:F,2,0),"") | M393: =+IFERROR(VLOOKUP(I393,BD_GICS!G:H,2,0),"")
A394: Credit | B394: MDLAT | C394: HUNT OIL | D394: 2836960 | E394: 3412 | F394: 34 | G394: 3412 | H394: 3412 | I394: 3412 | J394: =+IFERROR(VLOOKUP(F394,BD_GICS!A:B,2,0),"") -> Energy | K394: =+IFERROR(VLOOKUP(G394,BD_GICS!C:D,2,0),"") -> Exploration & Production | L394: =+IFERROR(VLOOKUP(H394,BD_GICS!E:F,2,0),"") | M394: =+IFERROR(VLOOKUP(I394,BD_GICS!G:H,2,0),"")
... A411: Credit | B411: MDLAT | C411: MINERVA | D411: 9122851.7 | E411: 3314 | F411: 33 | G411: 3314 | H411: 3314 | I411: 3314 | J411: =+IFERROR(VLOOKUP(F411,BD_GICS!A:B,2,0),"") -> Consumer Staples | K411: =+IFERROR(VLOOKUP(G411,BD_GICS!C:D,2,0),"") -> Food & Beverage | L411: =+IFERROR(VLOOKUP(H411,BD_GICS!E:F,2,0),"") | M411: =+IFERROR(VLOOKUP(I411,BD_GICS!G:H,2,0),"")
A412: Credit | B412: MDLAT | C412: MONEDA LATAM HY CREDIT FUND | D412: 2.5011007e+08 | E412: FUND | J412: =+IFERROR(VLOOKUP(F412,BD_GICS!A:B,2,0),"") | K412: =+IFERROR(VLOOKUP(G412,BD_GICS!C:D,2,0),"") | L412: =+IFERROR(VLOOKUP(H412,BD_GICS!E:F,2,0),"") | M412: =+IFERROR(VLOOKUP(I412,BD_GICS!G:H,2,0),"")
A413: Credit | B413: MDLAT | C413: MSU ENERGY | D413: 46073146 | E413: 3911 | F413: 39 | G413: 3911 | H413: 3911 | I413: 3911 | J413: =+IFERROR(VLOOKUP(F413,BD_GICS!A:B,2,0),"") -> Utilities | K413: =+IFERROR(VLOOKUP(G413,BD_GICS!C:D,2,0),"") -> Power Generation | L413: =+IFERROR(VLOOKUP(H413,BD_GICS!E:F,2,0),"") | M413: =+IFERROR(VLOOKUP(I413,BD_GICS!G:H,2,0),"")
A414: Credit | B414: MDLAT | C414: MULTIBANK | D414: 7507760.4 | E414: 3510 | F414: 35 | G414: 3510 | H414: 3510 | I414: 3510 | J414: =+IFERROR(VLOOKUP(F414,BD_GICS!A:B,2,0),"") -> Financials | K414: =+IFERROR(VLOOKUP(G414,BD_GICS!C:D,2,0),"") -> Banks | L414: =+IFERROR(VLOOKUP(H414,BD_GICS!E:F,2,0),"") | M414: =+IFERROR(VLOOKUP(I414,BD_GICS!G:H,2,0),"")
A415: Credit | B415: MDLAT | C415: MV24 CAPITAL | D415: 26980675 | E415: 3413 | F415: 34 | G415: 3413 | H415: 3413 | I415: 3413 | J415: =+IFERROR(VLOOKUP(F415,BD_GICS!A:B,2,0),"") -> Energy | K415: =+IFERROR(VLOOKUP(G415,BD_GICS!C:D,2,0),"") -> Oil & Gas Services & Equipment | L415: =+IFERROR(VLOOKUP(H415,BD_GICS!E:F,2,0),"") | M415: =+IFERROR(VLOOKUP(I415,BD_GICS!G:H,2,0),"")
A416: Credit | B416: MDLAT | C416: NATURA | D416: 809603.33 | E416: 1112111812 | F416: 11 | G416: 1112 | H416: 111211 | I416: 11121118 | J416: =+IFERROR(VLOOKUP(F416,BD_GICS!A:B,2,0),"") -> Consumer Discretionary | K416: =+IFERROR(VLOOKUP(G416,BD_GICS!C:D,2,0),"") -> Retail & Whsle - Discretionary | L416: =+IFERROR(VLOOKUP(H416,BD_GICS!E:F,2,0),"") -> Retail - Discretionary | M416: =+IFERROR(VLOOKUP(I416,BD_GICS!G:H,2,0),"") -> Other Spec Retail - Discr
A417: Credit | B417: MDLAT | C417: NOVA AUSTRAL | D417: 0 | E417: 12101010 | F417: 12 | G417: 1210 | H417: 121010 | I417: 12101010 | J417: =+IFERROR(VLOOKUP(F417,BD_GICS!A:B,2,0),"") -> Consumer Staples | K417: =+IFERROR(VLOOKUP(G417,BD_GICS!C:D,2,0),"") -> Consumer Staple Products | L417: =+IFERROR(VLOOKUP(H417,BD_GICS!E:F,2,0),"") -> Food | M417: =+IFERROR(VLOOKUP(I417,BD_GICS!G:H,2,0),"") -> Agricultural Producers
A418: Credit | B418: MDLAT | C418: OCEANOGRAFIA | D418: 77216.52 | E418: 3712 | F418: 37 | G418: 3712 | H418: 3712 | I418: 3712 | J418: =+IFERROR(VLOOKUP(F418,BD_GICS!A:B,2,0),"") -> Industrials | K418: =+IFERROR(VLOOKUP(G418,BD_GICS!C:D,2,0),"") -> Transportation & Logistics | L418: =+IFERROR(VLOOKUP(H418,BD_GICS!E:F,2,0),"") | M418: =+IFERROR(VLOOKUP(I418,BD_GICS!G:H,2,0),"")
A419: Credit | B419: MDLAT | C419: OCYAN | D419: 1.0883437e+08 | E419: 3413 | F419: 34 | G419: 3413 | H419: 3413 | I419: 3413 | J419: =+IFERROR(VLOOKUP(F419,BD_GICS!A:B,2,0),"") -> Energy | K419: =+IFERROR(VLOOKUP(G419,BD_GICS!C:D,2,0),"") -> Oil & Gas Services & Equipment | L419: =+IFERROR(VLOOKUP(H419,BD_GICS!E:F,2,0),"") | M419: =+IFERROR(VLOOKUP(I419,BD_GICS!G:H,2,0),"")
A420: Credit | B420: MDLAT | C420: OFFSHORE DRILLING HOLDING | D420: 19626 | E420: 3413 | F420: 34 | G420: 3413 | H420: 3413 | I420: 3413 | J420: =+IFERROR(VLOOKUP(F420,BD_GICS!A:B,2,0),"") -> Energy | K420: =+IFERROR(VLOOKUP(G420,BD_GICS!C:D,2,0),"") -> Oil & Gas Services & Equipment | L420: =+IFERROR(VLOOKUP(H420,BD_GICS!E:F,2,0),"") | M420: =+IFERROR(VLOOKUP(I420,BD_GICS!G:H,2,0),"")
A421: Credit | B421: MDLAT | C421: OGX PETROLEO E GAS | D421: 152481.02 | E421: 3412 | F421: 34 | G421: 3412 | H421: 3412 | I421: 3412 | J421: =+IFERROR(VLOOKUP(F421,BD_GICS!A:B,2,0),"") -> Energy | K421: =+IFERROR(VLOOKUP(G421,BD_GICS!C:D,2,0),"") -> Exploration & Production | L421: =+IFERROR(VLOOKUP(H421,BD_GICS!E:F,2,0),"") | M421: =+IFERROR(VLOOKUP(I421,BD_GICS!G:H,2,0),"")
A422: Credit | B422: MDLAT | C422: OPERADORA SERVICIOS MEGA | D422: 15869811 | E422: 3516 | F422: 35 | G422: 3516 | H422: 3516 | I422: 3516 | J422: =+IFERROR(VLOOKUP(F422,BD_GICS!A:B,2,0),"") -> Financials | K422: =+IFERROR(VLOOKUP(G422,BD_GICS!C:D,2,0),"") -> Financial Services | L422: =+IFERROR(VLOOKUP(H422,BD_GICS!E:F,2,0),"") | M422: =+IFERROR(VLOOKUP(I422,BD_GICS!G:H,2,0),"")
A423: Credit | B423: MDLAT | C423: ORO NEGRO DRILLING | D423: 470628.56 | E423: 3413 | F423: 34 | G423: 3413 | H423: 3413 | I423: 3413 | J423: =+IFERROR(VLOOKUP(F423,BD_GICS!A:B,2,0),"") -> Energy | K423: =+IFERROR(VLOOKUP(G423,BD_GICS!C:D,2,0),"") -> Oil & Gas Services & Equipment | L423: =+IFERROR(VLOOKUP(H423,BD_GICS!E:F,2,0),"") | M423: =+IFERROR(VLOOKUP(I423,BD_GICS!G:H,2,0),"")
A424: Credit | B424: MDLAT | C424: PAMPA ENERGIA | D424: 8192272.9 | E424: 3910 | F424: 39 | G424: 3910 | H424: 3910 | I424: 3910 | J424: =+IFERROR(VLOOKUP(F424,BD_GICS!A:B,2,0),"") -> Utilities | K424: =+IFERROR(VLOOKUP(G424,BD_GICS!C:D,2,0),"") -> Utilities | L424: =+IFERROR(VLOOKUP(H424,BD_GICS!E:F,2,0),"") | M424: =+IFERROR(VLOOKUP(I424,BD_GICS!G:H,2,0),"")
... A622: Credit | B622: MLATHY | C622: USJ ACUCAR E ALCOOL | D622: 1445034 | E622: 1210101014 | F622: 12 | G622: 1210 | H622: 121010 | I622: 12101010 | J622: =+IFERROR(VLOOKUP(F622,BD_GICS!A:B,2,0),"") -> Consumer Staples | K622: =+IFERROR(VLOOKUP(G622,BD_GICS!C:D,2,0),"") -> Consumer Staple Products | L622: =+IFERROR(VLOOKUP(H622,BD_GICS!E:F,2,0),"") -> Food | M622: =+IFERROR(VLOOKUP(I622,BD_GICS!G:H,2,0),"") -> Agricultural Producers
A623: Credit | B623: MLATHY | C623: VANGUARD HIGH DIVIDEND YIELD ETF | D623: 3188399.5 | E623: FUND | J623: =+IFERROR(VLOOKUP(F623,BD_GICS!A:B,2,0),"") | K623: =+IFERROR(VLOOKUP(G623,BD_GICS!C:D,2,0),"") | L623: =+IFERROR(VLOOKUP(H623,BD_GICS!E:F,2,0),"") | M623: =+IFERROR(VLOOKUP(I623,BD_GICS!G:H,2,0),"")
A624: Credit | B624: MLATHY | C624: WOM CHILE | D624: 1099980.9 | E624: 3113 | F624: 31 | G624: 3113 | H624: 3113 | I624: 3113 | J624: =+IFERROR(VLOOKUP(F624,BD_GICS!A:B,2,0),"") -> Communications | K624: =+IFERROR(VLOOKUP(G624,BD_GICS!C:D,2,0),"") -> Wireless Telecommunications Services | L624: =+IFERROR(VLOOKUP(H624,BD_GICS!E:F,2,0),"") | M624: =+IFERROR(VLOOKUP(I624,BD_GICS!G:H,2,0),"")
A625: Credit | B625: MLATHY | C625: YPF | D625: 2170832.9 | E625: 3410 | F625: 34 | G625: 3410 | H625: 3410 | I625: 3410 | J625: =+IFERROR(VLOOKUP(F625,BD_GICS!A:B,2,0),"") -> Energy | K625: =+IFERROR(VLOOKUP(G625,BD_GICS!C:D,2,0),"") -> Integrated Oils | L625: =+IFERROR(VLOOKUP(H625,BD_GICS!E:F,2,0),"") | M625: =+IFERROR(VLOOKUP(I625,BD_GICS!G:H,2,0),"")
A626: Credit | B626: MLATHY | C626: YPF ENERGIA ELECTRICA | D626: 2700987.1 | E626: 3911 | F626: 39 | G626: 3911 | H626: 3911 | I626: 3911 | J626: =+IFERROR(VLOOKUP(F626,BD_GICS!A:B,2,0),"") -> Utilities | K626: =+IFERROR(VLOOKUP(G626,BD_GICS!C:D,2,0),"") -> Power Generation | L626: =+IFERROR(VLOOKUP(H626,BD_GICS!E:F,2,0),"") | M626: =+IFERROR(VLOOKUP(I626,BD_GICS!G:H,2,0),"")
A627: Credit | B627: MLCC (LX) | C627: ABRA GROUP | D627: 3555403.4 | E627: 3213 | F627: 32 | G627: 3213 | H627: 3213 | I627: 3213 | J627: =+IFERROR(VLOOKUP(F627,BD_GICS!A:B,2,0),"") -> Consumer Discretionary | K627: =+IFERROR(VLOOKUP(G627,BD_GICS!C:D,2,0),"") -> Airlines | L627: =+IFERROR(VLOOKUP(H627,BD_GICS!E:F,2,0),"") | M627: =+IFERROR(VLOOKUP(I627,BD_GICS!G:H,2,0),"")
A628: Credit | B628: MLCC (LX) | C628: ACI AIRPORT SUDAMERICA | D628: 2549359.5 | E628: 3712 | F628: 37 | G628: 3712 | H628: 3712 | I628: 3712 | J628: =+IFERROR(VLOOKUP(F628,BD_GICS!A:B,2,0),"") -> Industrials | K628: =+IFERROR(VLOOKUP(G628,BD_GICS!C:D,2,0),"") -> Transportation & Logistics | L628: =+IFERROR(VLOOKUP(H628,BD_GICS!E:F,2,0),"") | M628: =+IFERROR(VLOOKUP(I628,BD_GICS!G:H,2,0),"")
A629: Credit | B629: MLCC (LX) | C629: ACU PETROLEO | D629: 2211251.2 | E629: 3415 | F629: 34 | G629: 3415 | H629: 3415 | I629: 3415 | J629: =+IFERROR(VLOOKUP(F629,BD_GICS!A:B,2,0),"") -> Energy | K629: =+IFERROR(VLOOKUP(G629,BD_GICS!C:D,2,0),"") -> Pipeline | L629: =+IFERROR(VLOOKUP(H629,BD_GICS!E:F,2,0),"") | M629: =+IFERROR(VLOOKUP(I629,BD_GICS!G:H,2,0),"")
A630: Credit | B630: MLCC (LX) | C630: AEGEA | D630: 1502820 | E630: 3910 | F630: 39 | G630: 3910 | H630: 3910 | I630: 3910 | J630: =+IFERROR(VLOOKUP(F630,BD_GICS!A:B,2,0),"") -> Utilities | K630: =+IFERROR(VLOOKUP(G630,BD_GICS!C:D,2,0),"") -> Utilities | L630: =+IFERROR(VLOOKUP(H630,BD_GICS!E:F,2,0),"") | M630: =+IFERROR(VLOOKUP(I630,BD_GICS!G:H,2,0),"")
A631: Credit | B631: MLCC (LX) | C631: AEROMEXICO | D631: 3025581.2 | E631: 1711121010 | F631: 17 | G631: 1711 | H631: 171112 | I631: 17111210 | J631: =+IFERROR(VLOOKUP(F631,BD_GICS!A:B,2,0),"") -> Industrials | K631: =+IFERROR(VLOOKUP(G631,BD_GICS!C:D,2,0),"") -> Industrial Services | L631: =+IFERROR(VLOOKUP(H631,BD_GICS!E:F,2,0),"") -> Transportation & Logistics | M631: =+IFERROR(VLOOKUP(I631,BD_GICS!G:H,2,0),"") -> Airlines
A632: Credit | B632: MLCC (LX) | C632: AEROPUERTO INTERNACIONAL DE QUITO | D632: 1915960.2 | E632: 3712 | F632: 37 | G632: 3712 | H632: 3712 | I632: 3712 | J632: =+IFERROR(VLOOKUP(F632,BD_GICS!A:B,2,0),"") -> Industrials | K632: =+IFERROR(VLOOKUP(G632,BD_GICS!C:D,2,0),"") -> Transportation & Logistics | L632: =+IFERROR(VLOOKUP(H632,BD_GICS!E:F,2,0),"") | M632: =+IFERROR(VLOOKUP(I632,BD_GICS!G:H,2,0),"")
A633: Credit | B633: MLCC (LX) | C633: AEROPUERTOS DOMINICANOS SIGLO XXI | D633: 801057.78 | E633: 3712 | F633: 37 | G633: 3712 | H633: 3712 | I633: 3712 | J633: =+IFERROR(VLOOKUP(F633,BD_GICS!A:B,2,0),"") -> Industrials | K633: =+IFERROR(VLOOKUP(G633,BD_GICS!C:D,2,0),"") -> Transportation & Logistics | L633: =+IFERROR(VLOOKUP(H633,BD_GICS!E:F,2,0),"") | M633: =+IFERROR(VLOOKUP(I633,BD_GICS!G:H,2,0),"")
A634: Credit | B634: MLCC (LX) | C634: AES ARGENTINA GENERACION | D634: 263758.33 | E634: 3911 | F634: 39 | G634: 3911 | H634: 3911 | I634: 3911 | J634: =+IFERROR(VLOOKUP(F634,BD_GICS!A:B,2,0),"") -> Utilities | K634: =+IFERROR(VLOOKUP(G634,BD_GICS!C:D,2,0),"") -> Power Generation | L634: =+IFERROR(VLOOKUP(H634,BD_GICS!E:F,2,0),"") | M634: =+IFERROR(VLOOKUP(I634,BD_GICS!G:H,2,0),"")
A635: Credit | B635: MLCC (LX) | C635: AES DOMINICANA | D635: 672647.92 | E635: 3910 | F635: 39 | G635: 3910 | H635: 3910 | I635: 3910 | J635: =+IFERROR(VLOOKUP(F635,BD_GICS!A:B,2,0),"") -> Utilities | K635: =+IFERROR(VLOOKUP(G635,BD_GICS!C:D,2,0),"") -> Utilities | L635: =+IFERROR(VLOOKUP(H635,BD_GICS!E:F,2,0),"") | M635: =+IFERROR(VLOOKUP(I635,BD_GICS!G:H,2,0),"")
... A903: Credit | B903: MLDL | C903: ESMAX | D903: 1564980.4 | E903: 3414 | F903: 34 | G903: 3414 | H903: 3414 | I903: 3414 | J903: =+IFERROR(VLOOKUP(F903,BD_GICS!A:B,2,0),"") -> Energy | K903: =+IFERROR(VLOOKUP(G903,BD_GICS!C:D,2,0),"") -> Refining & Marketing | L903: =+IFERROR(VLOOKUP(H903,BD_GICS!E:F,2,0),"") | M903: =+IFERROR(VLOOKUP(I903,BD_GICS!G:H,2,0),"")
...

Sheet BD_GICS
A1: SECTOR CODE | B1: SECTOR NAME | C1: INDUSTRY GROUP CODE | D1: INDUSTRY GROUP NAME | E1: INDUSTRY CODE | F1: INDUSTRY NAME | G1: SUB INDUSTRY CODE | H1: SUB INDUSTRY NAME
A2: 10 | B2: Communications | C2: 1010 | D2: Media | E2: 101010 | F2: Advertising & Marketing | G2: 10101010 | H2: Advertising & Marketing
A3: 10 | B3: Communications | C3: 1010 | D3: Media | E3: 101011 | F3: Cable & Satellite | G3: 10101110 | H3: Cable & Satellite
A4: 10 | B4: Communications | C4: 1010 | D4: Media | E4: 101012 | F4: Entertainment Content | G4: 10101210 | H4: Film & TV
A5: 10 | B5: Communications | C5: 1010 | D5: Media | E5: 101012 | F5: Entertainment Content | G5: 10101211 | H5: Music
A6: 10 | B6: Communications | C6: 1010 | D6: Media | E6: 101012 | F6: Entertainment Content | G6: 10101212 | H6: Video Games
A7: 10 | B7: Communications | C7: 1010 | D7: Media | E7: 101013 | F7: Publishing & Broadcasting | G7: 10101310 | H7: Publishing
A8: 10 | B8: Communications | C8: 1010 | D8: Media | E8: 101013 | F8: Publishing & Broadcasting | G8: 10101311 | H8: Local TV & Radio Broadcast
A9: 10 | B9: Communications | C9: 1010 | D9: Media | E9: 101013 | F9: Publishing & Broadcasting | G9: 10101312 | H9: Out-of-Home Display Advertising
A10: 10 | B10: Communications | C10: 1010 | D10: Media | E10: 101014 | F10: Internet Media & Services | G10: 10101410 | H10: Internet Media & Services
A11: 10 | B11: Communications | C11: 1011 | D11: Telecommunications | E11: 101110 | F11: Telecommunications | G11: 10111010 | H11: Wireless Telecommunications
A12: 10 | B12: Communications | C12: 1011 | D12: Telecommunications | E12: 101110 | F12: Telecommunications | G12: 10111011 | H12: Wireline Telecommunications
A13: 11 | B13: Consumer Discretionary | C13: 1110 | D13: Consumer Discretionary Products | E13: 111010 | F13: Apparel & Textile Products | G13: 11101010 | H13: Apparel, Footwear & Acc Design
... A215: 20 | B215: Utilities | C215: 2010 | D215: Utilities | E215: 201012 | F215: Elec & Gas Marketing & Trading | G215: 20101210 | H215: Elec & Gas Marketing & Trading
A216: 30 | B216: Materials | C216: 3010 | D216: Forest & Paper Products Manufacturing
A217: 30 | B217: Materials | C217: 3011 | D217: Metals & Mining
A218: 30 | B218: Materials | C218: 3012 | D218: Construction Materials Manufacturing
A219: 30 | B219: Materials | C219: 3013 | D219: Chemicals
A220: 30 | B220: Materials | C220: 3014 | D220: Containers & Packaging
A221: 31 | B221: Communications | C221: 3110 | D221: Cable & Satellite
A222: 31 | B222: Communications | C222: 3111 | D222: Wireline Telecommunications Services
A223: 31 | B223: Communications | C223: 3112 | D223: Internet Media
A224: 31 | B224: Communications | C224: 3113 | D224: Wireless Telecommunications Services
A225: 31 | B225: Communications | C225: 3114 | D225: Entertainment Content
A226: 31 | B226: Communications | C226: 3115 | D226: Publishing & Broadcasting
A227: 31 | B227: Communications | C227: 3116 | D227: Advertising & Marketing
... A294: 50 | B294: Government | C294: 5017 | D294: Government Local
